adcl/__init__.py
adcl/data_preprocessing.py
adcl-0.1.7.dist-info/LICENSE
adcl-0.1.7.dist-info/METADATA
adcl-0.1.7.dist-info/WHEEL
adcl-0.1.7.dist-info/top_level.txt
adcl-0.1.7.dist-info/RECORD
