Metadata-Version: 2.1
Name: adcl
Version: 0.1.7
Summary: Data preprocessing and cleaning tools for data science projects
Home-page: https://github.com/maykov-stepan/ADCL-Automatic-Data-Cleaning
Author: Maykov Stepan
Author-email: steve19992@mail.ru
License: MIT
Keywords: data cleaning,preprocessing,data science,machine learning
Classifier: Development Status :: 4 - Beta
Classifier: Intended Audience :: Developers
Classifier: Natural Language :: English
Classifier: License :: OSI Approved :: MIT License
Classifier: Programming Language :: Python :: 3.7
Classifier: Topic :: Software Development :: Libraries :: Python Modules
Classifier: Topic :: Scientific/Engineering :: Artificial Intelligence
Requires-Python: >=3.7,<3.8
License-File: LICENSE
Requires-Dist: numpy (<1.17.0,>=1.16.2)
Requires-Dist: matplotlib (==3.2.2)
Requires-Dist: adtk (>=0.6.2)
Requires-Dist: category-encoders (>=2.6.3)
Requires-Dist: dtaidistance
Requires-Dist: matrixprofile (>=1.1.10)
Requires-Dist: mxnet (==1.7.0.post2)
